README.txt
setup.py
collective/__init__.py
collective.portlet.twittertrackback.egg-info/PKG-INFO
collective.portlet.twittertrackback.egg-info/SOURCES.txt
collective.portlet.twittertrackback.egg-info/dependency_links.txt
collective.portlet.twittertrackback.egg-info/entry_points.txt
collective.portlet.twittertrackback.egg-info/namespace_packages.txt
collective.portlet.twittertrackback.egg-info/not-zip-safe
collective.portlet.twittertrackback.egg-info/requires.txt
collective.portlet.twittertrackback.egg-info/top_level.txt
collective/portlet/__init__.py
collective/portlet/twittertrackback/__init__.py
collective/portlet/twittertrackback/configure.zcml
collective/portlet/twittertrackback/twittertrackback.pt
collective/portlet/twittertrackback/twittertrackback.py
collective/portlet/twittertrackback/version.txt
collective/portlet/twittertrackback/profiles/default/metadata.xml
collective/portlet/twittertrackback/profiles/default/portlets.xml
collective/portlet/twittertrackback/tests/__init__.py
collective/portlet/twittertrackback/tests/base.py
collective/portlet/twittertrackback/tests/test_portlet.py
docs/HISTORY.txt
docs/INSTALL.txt
docs/LICENSE.GPL
docs/LICENSE.txt