Metadata-Version: 1.0
Name: collective.portlet.twittertrackback
Version: 1.0
Summary: A portlet that displays mentions of the current page's url via Topsy
Home-page: http://plone.org/collective.portlet.twittertrackback
Author: Matt Hamilton
Author-email: matth@netsight.co.uk
License: GPL
Keywords: plone twitter topsy portlet
Platform: UNKNOWN
Classifier: Framework :: Plone
Classifier: Programming Language :: Python
